chytorch/zoo/rxnmap/__init__.py
chytorch/zoo/rxnmap/weights.pt
chytorch_rxnmap_synplan-1.6.dist-info/LICENSE
chytorch_rxnmap_synplan-1.6.dist-info/METADATA
chytorch_rxnmap_synplan-1.6.dist-info/WHEEL
chytorch_rxnmap_synplan-1.6.dist-info/RECORD
