Metadata-Version: 2.3
Name: chytorch-rxnmap-synplan
Version: 1.6
Summary: 
License: LGPL-3.0-or-later
Keywords: scientific engineering,chemistry,information analysis,software development,libraries
Author: Dr. Ramil Nugmanov
Author-email: nougmanoff@protonmail.com
Requires-Python: >=3.10
Classifier: Environment :: Plugins
Classifier: Intended Audience :: Science/Research
Classifier: License :: OSI Approved :: GNU Lesser General Public License v3 or later (LGPLv3+)
Classifier: Operating System :: OS Independent
Classifier: Programming Language :: Python
Classifier: Programming Language :: Python :: 3
Classifier: Programming Language :: Python :: 3.10
Classifier: Programming Language :: Python :: 3.11
Classifier: Programming Language :: Python :: 3.12
Classifier: Programming Language :: Python :: 3.13
Classifier: Programming Language :: Python :: 3 :: Only
Classifier: Topic :: Scientific/Engineering
Classifier: Topic :: Scientific/Engineering :: Chemistry
Classifier: Topic :: Scientific/Engineering :: Information Analysis
Classifier: Topic :: Software Development
Classifier: Topic :: Software Development :: Libraries
Classifier: Topic :: Software Development :: Libraries :: Python Modules
Requires-Dist: chytorch-synplan (>=1.69)
Project-URL: Homepage, https://github.com/chython/chytorch-rxnmap
Project-URL: Repository, https://github.com/chython/chytorch-rxnmap
